service_framework/__init__.py
service_framework/__main__.py
service_framework/inline_services.py
service_framework/service.py
service_framework/connections/__init__.py
service_framework/connections/in/__init__.py
service_framework/connections/in/replyer.py
service_framework/connections/in/subscriber.py
service_framework/connections/out/__init__.py
service_framework/connections/out/external_request.py
service_framework/connections/out/publisher.py
service_framework/connections/out/requester.py
service_framework/states/__init__.py
service_framework/states/in/__init__.py
service_framework/states/in/delta_update_in.py
service_framework/states/in/full_update_in.py
service_framework/states/out/__init__.py
service_framework/states/out/delta_update_out.py
service_framework/states/out/full_update_out.py
service_framework/utils/__init__.py
service_framework/utils/config_utils.py
service_framework/utils/connection_utils.py
service_framework/utils/constants.py
service_framework/utils/logging_utils.py
service_framework/utils/msgpack_utils.py
service_framework/utils/service_utils.py
service_framework/utils/socket_utils.py
service_framework/utils/state_utils.py
service_framework/utils/update_utils.py
service_framework/utils/utils.py
service_framework/utils/validation_utils.py
service_framework-0.0.20.dist-info/LICENSE.txt
service_framework-0.0.20.dist-info/METADATA
service_framework-0.0.20.dist-info/WHEEL
service_framework-0.0.20.dist-info/entry_points.txt
service_framework-0.0.20.dist-info/top_level.txt
service_framework-0.0.20.dist-info/RECORD
