Metadata-Version: 2.1
Name: service-framework
Version: 0.0.20
Summary: A package for re-defining microservice architecture
Home-page: https://github.com/ZacharyATanenbaum/service_framework
Author: Zachary A. Tanenbaum
Author-email: ZachTanenbaum+service_framework@gmail.com
License: UNKNOWN
Platform: UNKNOWN
Classifier: Programming Language :: Python :: 3
Classifier: License :: OSI Approved :: MIT License
Classifier: Operating System :: OS Independent
Requires-Python: >=3.6
